{
  "hash": "031524344651",
  "decodedHash": [
    {
      "0": 3
    },
    {
      "1": 5
    },
    {
      "2": 4
    },
    {
      "3": 4
    },
    {
      "4": 6
    },
    {
      "5": 1
    }
  ],
  "edition": 3,
  "date": 1667902388654,
  "attributes": [
    {
      "id": 3,
      "layer": "BG",
      "name": "11",
      "rarity": 7.142857142857142
    },
    {
      "id": 5,
      "layer": "BODY",
      "name": "5",
      "rarity": 20
    },
    {
      "id": 4,
      "layer": "EYES",
      "name": "4",
      "rarity": 20
    },
    {
      "id": 4,
      "layer": "OUTFITS",
      "name": "4",
      "rarity": 14.285714285714285
    },
    {
      "id": 6,
      "layer": "BEARD",
      "name": "6",
      "rarity": 11.111111111111112
    },
    {
      "id": 1,
      "layer": "GLASSES",
      "name": "1",
      "rarity": 20
    }
  ]
}